{
  "profile": {
    "name": "Dario Mennillo"
  },
  "plants": [
    {
      "id": "1",
      "price": "9.90",
      "name": "Monstera Obliqua",
      "image": "./img/monstera_obliqua.webp",
      "descAlt": "Pianta sempreverde di Monstera Obliqua",
      "produttore": "Dario"
    },
    {
      "id": "2",
      "price": "5.60",
      "name": "Crassula",
      "image": "./img/crassula.webp",
      "descAlt": "Pianta di crassula o albero di giada",
      "produttore": "Anna"
    },
    {
      "id": "3",
      "price": "11.90",
      "name": "San Severia",
      "image": "./img/sanseveria.webp",
      "descAlt": "Pianta di sanseviera, quasi indistruttibile",
      "produttore": "Maria"
    }
  ],
  "carrello": [
    {
      "id": "2",
      "prezzo": "5.60",
      "nome": "Crassula"
    },
    {
      "id": "1",
      "prezzo": "9.90",
      "nome": "Monstera Obliqua"
    },
    {
      "id": "3",
      "prezzo": "11.90",
      "nome": "San Severia"
    },
    {
      "id": "2",
      "prezzo": "5.60",
      "nome": "Crassula"
    },
    {
      "id": "1",
      "prezzo": "9.90",
      "nome": "Monstera Obliqua"
    }
  ],
  "Logstorico": [
    {
      "id": "0",
      "idCarello": 1,
      "idCliente": 53
    }
  ],

  "acquisti":[
    
  ]
}